morphantic_core/__init__.py
morphantic_core/client.py
morphantic_core-0.1.1.dist-info/licenses/LICENSE
morphantic_core-0.1.1.dist-info/METADATA
morphantic_core-0.1.1.dist-info/WHEEL
morphantic_core-0.1.1.dist-info/entry_points.txt
morphantic_core-0.1.1.dist-info/top_level.txt
morphantic_core-0.1.1.dist-info/RECORD
