Metadata-Version: 2.4
Name: morphantic-core
Version: 0.1.1
Summary: Morphantic Core: modular evolutionary optimization with safe exploration, drift guard, and Optuna integration.
Author-email: Morphantic <help@morphantic.com>
License: Apache-2.0
Project-URL: Homepage, https://github.com/morphantic/morphantic-core
Project-URL: Issues, https://github.com/morphantic/morphantic-core/issues
Keywords: optimization,evolutionary,optuna,surrogate,trust-region
Classifier: Programming Language :: Python :: 3
Classifier: License :: OSI Approved :: Apache Software License
Classifier: Operating System :: OS Independent
Requires-Python: >=3.9
License-File: LICENSE
Requires-Dist: numpy<3.0,>=1.23
Requires-Dist: requests<3.0,>=2.28
Requires-Dist: pydantic<3.0,>=2.0
Provides-Extra: server
Requires-Dist: fastapi<1.0,>=0.110; extra == "server"
Requires-Dist: uvicorn[standard]<1.0,>=0.23; extra == "server"
Requires-Dist: requests<3.0,>=2.28; extra == "server"
Requires-Dist: pydantic<3.0,>=2.0; extra == "server"
Provides-Extra: sklearn
Requires-Dist: scikit-learn<2.0,>=1.1; extra == "sklearn"
Requires-Dist: numpy<3.0,>=1.23; extra == "sklearn"
Provides-Extra: all
Requires-Dist: numpy<3.0,>=1.23; extra == "all"
Requires-Dist: requests<3.0,>=2.28; extra == "all"
Requires-Dist: pydantic<3.0,>=2.0; extra == "all"
Requires-Dist: fastapi<1.0,>=0.110; extra == "all"
Requires-Dist: uvicorn[standard]<1.0,>=0.23; extra == "all"
Requires-Dist: scikit-learn<2.0,>=1.1; extra == "all"
Dynamic: license-file
